<?xml version="1.0" encoding="utf-8" ?>
<c2layout>
    <name>GameLayout</name>
    <event-sheet>GameEvent</event-sheet>
    <size>
        <width>1216</width>
        <height>892</height>
    </size>
    <margins>
        <horizontal>500</horizontal>
        <vertical>500</vertical>
    </margins>
    <unbounded-scrolling>0</unbounded-scrolling>
    <layers>
        <layer name="Background">
            <initially-visible>1</initially-visible>
            <background-color>0,0,0</background-color>
            <transparent>0</transparent>
            <parallax>
                <x>1</x>
                <y>1</y>
            </parallax>
            <zoom-rate>1</zoom-rate>
            <opacity>1</opacity>
            <force-own-texture>0</force-own-texture>
            <instances>
                <instance type="TiledBackground">
                    <properties>
                        <initial-visibility>Visible</initial-visibility>
                        <effect>(none)</effect>
                        <hotspot>Top-left</hotspot>
                    </properties>
                    <world>
                        <x>40</x>
                        <y>0</y>
                        <z>0</z>
                        <width>1176</width>
                        <height>892</height>
                        <depth>0</depth>
                        <hotspotX>0</hotspotX>
                        <hotspotY>0</hotspotY>
                        <angle>0</angle>
                        <opacity>1</opacity>
                    </world>
                </instance>
            </instances>
        </layer>
        <layer name="GameMain">
            <initially-visible>1</initially-visible>
            <background-color>255,255,255</background-color>
            <transparent>1</transparent>
            <parallax>
                <x>1</x>
                <y>1</y>
            </parallax>
            <zoom-rate>1</zoom-rate>
            <opacity>1</opacity>
            <force-own-texture>0</force-own-texture>
            <instances>
                <instance type="player">
                    <properties>
                        <initial-visibility>Visible</initial-visibility>
                        <initial-frame>0</initial-frame>
                        <effect>(none)</effect>
                    </properties>
                    <behavior-instances>
                        <behavior-instance type="8Direction">
                            <properties>
                                <max-speed>200</max-speed>
                                <acceleration>600</acceleration>
                                <deceleration>500</deceleration>
                                <directions>8 directions</directions>
                                <set-angle>360 degree (smooth)</set-angle>
                                <default-controls>Yes</default-controls>
                            </properties>
                        </behavior-instance>
                        <behavior-instance type="ScrollTo" />
                    </behavior-instances>
                    <world>
                        <x>1098</x>
                        <y>81</y>
                        <z>0</z>
                        <width>25</width>
                        <height>25</height>
                        <depth>0</depth>
                        <hotspotX>0.533333361</hotspotX>
                        <hotspotY>0.533333361</hotspotY>
                        <angle>0</angle>
                        <opacity>1</opacity>
                    </world>
                </instance>
                <instance type="wall">
                    <properties>
                        <initial-visibility>Invisible</initial-visibility>
                        <initial-frame>0</initial-frame>
                        <effect>(none)</effect>
                    </properties>
                    <behavior-instances>
                        <behavior-instance type="Solid" />
                    </behavior-instances>
                    <world>
                        <x>1110</x>
                        <y>238</y>
                        <z>0</z>
                        <width>124</width>
                        <height>36</height>
                        <depth>0</depth>
                        <hotspotX>0.5</hotspotX>
                        <hotspotY>0.5</hotspotY>
                        <angle>0</angle>
                        <opacity>1</opacity>
                    </world>
                </instance>
                <instance type="wall">
                    <properties>
                        <initial-visibility>Invisible</initial-visibility>
                        <initial-frame>0</initial-frame>
                        <effect>(none)</effect>
                    </properties>
                    <behavior-instances>
                        <behavior-instance type="Solid" />
                    </behavior-instances>
                    <world>
                        <x>938.5</x>
                        <y>317.5</y>
                        <z>0</z>
                        <width>259</width>
                        <height>39</height>
                        <depth>0</depth>
                        <hotspotX>0.5</hotspotX>
                        <hotspotY>0.5</hotspotY>
                        <angle>0</angle>
                        <opacity>1</opacity>
                    </world>
                </instance>
                <instance type="wall">
                    <properties>
                        <initial-visibility>Invisible</initial-visibility>
                        <initial-frame>0</initial-frame>
                        <effect>(none)</effect>
                    </properties>
                    <behavior-instances>
                        <behavior-instance type="Solid" />
                    </behavior-instances>
                    <world>
                        <x>1109.5</x>
                        <y>442.5</y>
                        <z>0</z>
                        <width>127</width>
                        <height>33</height>
                        <depth>0</depth>
                        <hotspotX>0.5</hotspotX>
                        <hotspotY>0.5</hotspotY>
                        <angle>0</angle>
                        <opacity>1</opacity>
                    </world>
                </instance>
                <instance type="wall">
                    <properties>
                        <initial-visibility>Invisible</initial-visibility>
                        <initial-frame>0</initial-frame>
                        <effect>(none)</effect>
                    </properties>
                    <behavior-instances>
                        <behavior-instance type="Solid" />
                    </behavior-instances>
                    <world>
                        <x>895</x>
                        <y>444.5</y>
                        <z>0</z>
                        <width>172</width>
                        <height>41</height>
                        <depth>0</depth>
                        <hotspotX>0.5</hotspotX>
                        <hotspotY>0.5</hotspotY>
                        <angle>0</angle>
                        <opacity>1</opacity>
                    </world>
                </instance>
                <instance type="wall">
                    <properties>
                        <initial-visibility>Invisible</initial-visibility>
                        <initial-frame>0</initial-frame>
                        <effect>(none)</effect>
                    </properties>
                    <behavior-instances>
                        <behavior-instance type="Solid" />
                    </behavior-instances>
                    <world>
                        <x>924</x>
                        <y>523.5</y>
                        <z>0</z>
                        <width>38</width>
                        <height>117</height>
                        <depth>0</depth>
                        <hotspotX>0.5</hotspotX>
                        <hotspotY>0.5</hotspotY>
                        <angle>0</angle>
                        <opacity>1</opacity>
                    </world>
                </instance>
                <instance type="wall">
                    <properties>
                        <initial-visibility>Invisible</initial-visibility>
                        <initial-frame>0</initial-frame>
                        <effect>(none)</effect>
                    </properties>
                    <behavior-instances>
                        <behavior-instance type="Solid" />
                    </behavior-instances>
                    <world>
                        <x>792.5</x>
                        <y>351</y>
                        <z>0</z>
                        <width>29</width>
                        <height>618</height>
                        <depth>0</depth>
                        <hotspotX>0.5</hotspotX>
                        <hotspotY>0.5</hotspotY>
                        <angle>0</angle>
                        <opacity>1</opacity>
                    </world>
                </instance>
                <instance type="wall">
                    <properties>
                        <initial-visibility>Invisible</initial-visibility>
                        <initial-frame>0</initial-frame>
                        <effect>(none)</effect>
                    </properties>
                    <behavior-instances>
                        <behavior-instance type="Solid" />
                    </behavior-instances>
                    <world>
                        <x>1021.5</x>
                        <y>645.5</y>
                        <z>0</z>
                        <width>301</width>
                        <height>39</height>
                        <depth>0</depth>
                        <hotspotX>0.5</hotspotX>
                        <hotspotY>0.5</hotspotY>
                        <angle>0</angle>
                        <opacity>1</opacity>
                    </world>
                </instance>
                <instance type="wall">
                    <properties>
                        <initial-visibility>Invisible</initial-visibility>
                        <initial-frame>0</initial-frame>
                        <effect>(none)</effect>
                    </properties>
                    <behavior-instances>
                        <behavior-instance type="Solid" />
                    </behavior-instances>
                    <world>
                        <x>956</x>
                        <y>779.5</y>
                        <z>0</z>
                        <width>28</width>
                        <height>139</height>
                        <depth>0</depth>
                        <hotspotX>0.5</hotspotX>
                        <hotspotY>0.5</hotspotY>
                        <angle>0</angle>
                        <opacity>1</opacity>
                    </world>
                </instance>
                <instance type="wall">
                    <properties>
                        <initial-visibility>Invisible</initial-visibility>
                        <initial-frame>0</initial-frame>
                        <effect>(none)</effect>
                    </properties>
                    <behavior-instances>
                        <behavior-instance type="Solid" />
                    </behavior-instances>
                    <world>
                        <x>730</x>
                        <y>641</y>
                        <z>0</z>
                        <width>92</width>
                        <height>40</height>
                        <depth>0</depth>
                        <hotspotX>0.5</hotspotX>
                        <hotspotY>0.5</hotspotY>
                        <angle>0</angle>
                        <opacity>1</opacity>
                    </world>
                </instance>
                <instance type="wall">
                    <properties>
                        <initial-visibility>Invisible</initial-visibility>
                        <initial-frame>0</initial-frame>
                        <effect>(none)</effect>
                    </properties>
                    <behavior-instances>
                        <behavior-instance type="Solid" />
                    </behavior-instances>
                    <world>
                        <x>697.5</x>
                        <y>730.5</y>
                        <z>0</z>
                        <width>29</width>
                        <height>139</height>
                        <depth>0</depth>
                        <hotspotX>0.5</hotspotX>
                        <hotspotY>0.5</hotspotY>
                        <angle>0</angle>
                        <opacity>1</opacity>
                    </world>
                </instance>
                <instance type="wall">
                    <properties>
                        <initial-visibility>Invisible</initial-visibility>
                        <initial-frame>0</initial-frame>
                        <effect>(none)</effect>
                    </properties>
                    <behavior-instances>
                        <behavior-instance type="Solid" />
                    </behavior-instances>
                    <world>
                        <x>1194</x>
                        <y>448</y>
                        <z>0</z>
                        <width>40</width>
                        <height>880</height>
                        <depth>0</depth>
                        <hotspotX>0.5</hotspotX>
                        <hotspotY>0.5</hotspotY>
                        <angle>0</angle>
                        <opacity>1</opacity>
                    </world>
                </instance>
                <instance type="wall">
                    <properties>
                        <initial-visibility>Invisible</initial-visibility>
                        <initial-frame>0</initial-frame>
                        <effect>(none)</effect>
                    </properties>
                    <behavior-instances>
                        <behavior-instance type="Solid" />
                    </behavior-instances>
                    <world>
                        <x>694</x>
                        <y>201</y>
                        <z>0</z>
                        <width>72</width>
                        <height>40</height>
                        <depth>0</depth>
                        <hotspotX>0.5</hotspotX>
                        <hotspotY>0.5</hotspotY>
                        <angle>0</angle>
                        <opacity>1</opacity>
                    </world>
                </instance>
                <instance type="wall">
                    <properties>
                        <initial-visibility>Invisible</initial-visibility>
                        <initial-frame>0</initial-frame>
                        <effect>(none)</effect>
                    </properties>
                    <behavior-instances>
                        <behavior-instance type="Solid" />
                    </behavior-instances>
                    <world>
                        <x>706.5</x>
                        <y>497</y>
                        <z>0</z>
                        <width>41</width>
                        <height>112</height>
                        <depth>0</depth>
                        <hotspotX>0.5</hotspotX>
                        <hotspotY>0.5</hotspotY>
                        <angle>0</angle>
                        <opacity>1</opacity>
                    </world>
                </instance>
                <instance type="wall">
                    <properties>
                        <initial-visibility>Invisible</initial-visibility>
                        <initial-frame>0</initial-frame>
                        <effect>(none)</effect>
                    </properties>
                    <behavior-instances>
                        <behavior-instance type="Solid" />
                    </behavior-instances>
                    <world>
                        <x>573</x>
                        <y>457.5</y>
                        <z>0</z>
                        <width>222</width>
                        <height>35</height>
                        <depth>0</depth>
                        <hotspotX>0.5</hotspotX>
                        <hotspotY>0.5</hotspotY>
                        <angle>0</angle>
                        <opacity>1</opacity>
                    </world>
                </instance>
                <instance type="wall">
                    <properties>
                        <initial-visibility>Invisible</initial-visibility>
                        <initial-frame>0</initial-frame>
                        <effect>(none)</effect>
                    </properties>
                    <behavior-instances>
                        <behavior-instance type="Solid" />
                    </behavior-instances>
                    <world>
                        <x>543</x>
                        <y>200</y>
                        <z>0</z>
                        <width>148</width>
                        <height>44</height>
                        <depth>0</depth>
                        <hotspotX>0.5</hotspotX>
                        <hotspotY>0.5</hotspotY>
                        <angle>0</angle>
                        <opacity>1</opacity>
                    </world>
                </instance>
                <instance type="wall">
                    <properties>
                        <initial-visibility>Invisible</initial-visibility>
                        <initial-frame>0</initial-frame>
                        <effect>(none)</effect>
                    </properties>
                    <behavior-instances>
                        <behavior-instance type="Solid" />
                    </behavior-instances>
                    <world>
                        <x>583.5</x>
                        <y>370</y>
                        <z>0</z>
                        <width>35</width>
                        <height>136</height>
                        <depth>0</depth>
                        <hotspotX>0.5</hotspotX>
                        <hotspotY>0.5</hotspotY>
                        <angle>0</angle>
                        <opacity>1</opacity>
                    </world>
                </instance>
                <instance type="wall">
                    <properties>
                        <initial-visibility>Invisible</initial-visibility>
                        <initial-frame>0</initial-frame>
                        <effect>(none)</effect>
                    </properties>
                    <behavior-instances>
                        <behavior-instance type="Solid" />
                    </behavior-instances>
                    <world>
                        <x>543.5</x>
                        <y>317.5</y>
                        <z>0</z>
                        <width>45</width>
                        <height>28.999998093</height>
                        <depth>0</depth>
                        <hotspotX>0.5</hotspotX>
                        <hotspotY>0.5</hotspotY>
                        <angle>0</angle>
                        <opacity>1</opacity>
                    </world>
                </instance>
                <instance type="wall">
                    <properties>
                        <initial-visibility>Invisible</initial-visibility>
                        <initial-frame>0</initial-frame>
                        <effect>(none)</effect>
                    </properties>
                    <behavior-instances>
                        <behavior-instance type="Solid" />
                    </behavior-instances>
                    <world>
                        <x>448.5</x>
                        <y>107</y>
                        <z>0</z>
                        <width>37</width>
                        <height>134</height>
                        <depth>0</depth>
                        <hotspotX>0.5</hotspotX>
                        <hotspotY>0.5</hotspotY>
                        <angle>0</angle>
                        <opacity>1</opacity>
                    </world>
                </instance>
                <instance type="wall">
                    <properties>
                        <initial-visibility>Invisible</initial-visibility>
                        <initial-frame>0</initial-frame>
                        <effect>(none)</effect>
                    </properties>
                    <behavior-instances>
                        <behavior-instance type="Solid" />
                    </behavior-instances>
                    <world>
                        <x>585</x>
                        <y>590</y>
                        <z>0</z>
                        <width>34</width>
                        <height>222</height>
                        <depth>0</depth>
                        <hotspotX>0.5</hotspotX>
                        <hotspotY>0.5</hotspotY>
                        <angle>0</angle>
                        <opacity>1</opacity>
                    </world>
                </instance>
                <instance type="wall">
                    <properties>
                        <initial-visibility>Invisible</initial-visibility>
                        <initial-frame>0</initial-frame>
                        <effect>(none)</effect>
                    </properties>
                    <behavior-instances>
                        <behavior-instance type="Solid" />
                    </behavior-instances>
                    <world>
                        <x>696.5</x>
                        <y>732</y>
                        <z>0</z>
                        <width>27</width>
                        <height>136</height>
                        <depth>0</depth>
                        <hotspotX>0.5</hotspotX>
                        <hotspotY>0.5</hotspotY>
                        <angle>0</angle>
                        <opacity>1</opacity>
                    </world>
                </instance>
                <instance type="wall">
                    <properties>
                        <initial-visibility>Invisible</initial-visibility>
                        <initial-frame>0</initial-frame>
                        <effect>(none)</effect>
                    </properties>
                    <behavior-instances>
                        <behavior-instance type="Solid" />
                    </behavior-instances>
                    <world>
                        <x>481</x>
                        <y>731</y>
                        <z>0</z>
                        <width>108</width>
                        <height>38</height>
                        <depth>0</depth>
                        <hotspotX>0.5</hotspotX>
                        <hotspotY>0.5</hotspotY>
                        <angle>0</angle>
                        <opacity>1</opacity>
                    </world>
                </instance>
                <instance type="wall">
                    <properties>
                        <initial-visibility>Invisible</initial-visibility>
                        <initial-frame>0</initial-frame>
                        <effect>(none)</effect>
                    </properties>
                    <behavior-instances>
                        <behavior-instance type="Solid" />
                    </behavior-instances>
                    <world>
                        <x>408.5</x>
                        <y>663.5</y>
                        <z>0</z>
                        <width>35</width>
                        <height>371</height>
                        <depth>0</depth>
                        <hotspotX>0.5</hotspotX>
                        <hotspotY>0.5</hotspotY>
                        <angle>0</angle>
                        <opacity>1</opacity>
                    </world>
                </instance>
                <instance type="wall">
                    <properties>
                        <initial-visibility>Invisible</initial-visibility>
                        <initial-frame>0</initial-frame>
                        <effect>(none)</effect>
                    </properties>
                    <behavior-instances>
                        <behavior-instance type="Solid" />
                    </behavior-instances>
                    <world>
                        <x>446</x>
                        <y>355</y>
                        <z>0</z>
                        <width>30</width>
                        <height>106</height>
                        <depth>0</depth>
                        <hotspotX>0.5</hotspotX>
                        <hotspotY>0.5</hotspotY>
                        <angle>0</angle>
                        <opacity>1</opacity>
                    </world>
                </instance>
                <instance type="wall">
                    <properties>
                        <initial-visibility>Invisible</initial-visibility>
                        <initial-frame>0</initial-frame>
                        <effect>(none)</effect>
                    </properties>
                    <behavior-instances>
                        <behavior-instance type="Solid" />
                    </behavior-instances>
                    <world>
                        <x>468.5</x>
                        <y>316</y>
                        <z>0</z>
                        <width>13</width>
                        <height>26</height>
                        <depth>0</depth>
                        <hotspotX>0.5</hotspotX>
                        <hotspotY>0.5</hotspotY>
                        <angle>0</angle>
                        <opacity>1</opacity>
                    </world>
                </instance>
                <instance type="wall">
                    <properties>
                        <initial-visibility>Invisible</initial-visibility>
                        <initial-frame>0</initial-frame>
                        <effect>(none)</effect>
                    </properties>
                    <behavior-instances>
                        <behavior-instance type="Solid" />
                    </behavior-instances>
                    <world>
                        <x>450</x>
                        <y>214.5</y>
                        <z>0</z>
                        <width>38</width>
                        <height>79</height>
                        <depth>0</depth>
                        <hotspotX>0.5</hotspotX>
                        <hotspotY>0.5</hotspotY>
                        <angle>0</angle>
                        <opacity>1</opacity>
                    </world>
                </instance>
                <instance type="wall">
                    <properties>
                        <initial-visibility>Invisible</initial-visibility>
                        <initial-frame>0</initial-frame>
                        <effect>(none)</effect>
                    </properties>
                    <behavior-instances>
                        <behavior-instance type="Solid" />
                    </behavior-instances>
                    <world>
                        <x>425.5</x>
                        <y>443</y>
                        <z>0</z>
                        <width>71</width>
                        <height>70</height>
                        <depth>0</depth>
                        <hotspotX>0.5</hotspotX>
                        <hotspotY>0.5</hotspotY>
                        <angle>0</angle>
                        <opacity>1</opacity>
                    </world>
                </instance>
                <instance type="wall">
                    <properties>
                        <initial-visibility>Invisible</initial-visibility>
                        <initial-frame>0</initial-frame>
                        <effect>(none)</effect>
                    </properties>
                    <behavior-instances>
                        <behavior-instance type="Solid" />
                    </behavior-instances>
                    <world>
                        <x>335</x>
                        <y>433.5</y>
                        <z>0</z>
                        <width>108</width>
                        <height>49</height>
                        <depth>0</depth>
                        <hotspotX>0.5</hotspotX>
                        <hotspotY>0.5</hotspotY>
                        <angle>0</angle>
                        <opacity>1</opacity>
                    </world>
                </instance>
                <instance type="wall">
                    <properties>
                        <initial-visibility>Invisible</initial-visibility>
                        <initial-frame>0</initial-frame>
                        <effect>(none)</effect>
                    </properties>
                    <behavior-instances>
                        <behavior-instance type="Solid" />
                    </behavior-instances>
                    <world>
                        <x>296.5</x>
                        <y>292.5</y>
                        <z>0</z>
                        <width>33</width>
                        <height>228.999984741</height>
                        <depth>0</depth>
                        <hotspotX>0.5</hotspotX>
                        <hotspotY>0.5</hotspotY>
                        <angle>0</angle>
                        <opacity>1</opacity>
                    </world>
                </instance>
                <instance type="wall">
                    <properties>
                        <initial-visibility>Invisible</initial-visibility>
                        <initial-frame>0</initial-frame>
                        <effect>(none)</effect>
                    </properties>
                    <behavior-instances>
                        <behavior-instance type="Solid" />
                    </behavior-instances>
                    <world>
                        <x>348</x>
                        <y>192</y>
                        <z>0</z>
                        <width>66</width>
                        <height>28</height>
                        <depth>0</depth>
                        <hotspotX>0.5</hotspotX>
                        <hotspotY>0.5</hotspotY>
                        <angle>0</angle>
                        <opacity>1</opacity>
                    </world>
                </instance>
                <instance type="wall">
                    <properties>
                        <initial-visibility>Invisible</initial-visibility>
                        <initial-frame>0</initial-frame>
                        <effect>(none)</effect>
                    </properties>
                    <behavior-instances>
                        <behavior-instance type="Solid" />
                    </behavior-instances>
                    <world>
                        <x>469.5</x>
                        <y>316</y>
                        <z>0</z>
                        <width>15</width>
                        <height>26</height>
                        <depth>0</depth>
                        <hotspotX>0.5</hotspotX>
                        <hotspotY>0.5</hotspotY>
                        <angle>0</angle>
                        <opacity>1</opacity>
                    </world>
                </instance>
                <instance type="wall">
                    <properties>
                        <initial-visibility>Invisible</initial-visibility>
                        <initial-frame>0</initial-frame>
                        <effect>(none)</effect>
                    </properties>
                    <behavior-instances>
                        <behavior-instance type="Solid" />
                    </behavior-instances>
                    <world>
                        <x>204</x>
                        <y>648.5</y>
                        <z>0</z>
                        <width>238</width>
                        <height>43</height>
                        <depth>0</depth>
                        <hotspotX>0.5</hotspotX>
                        <hotspotY>0.5</hotspotY>
                        <angle>0</angle>
                        <opacity>1</opacity>
                    </world>
                </instance>
                <instance type="wall">
                    <properties>
                        <initial-visibility>Invisible</initial-visibility>
                        <initial-frame>0</initial-frame>
                        <effect>(none)</effect>
                    </properties>
                    <behavior-instances>
                        <behavior-instance type="Solid" />
                    </behavior-instances>
                    <world>
                        <x>119.5</x>
                        <y>870.5</y>
                        <z>0</z>
                        <width>155</width>
                        <height>37</height>
                        <depth>0</depth>
                        <hotspotX>0.5</hotspotX>
                        <hotspotY>0.5</hotspotY>
                        <angle>0</angle>
                        <opacity>1</opacity>
                    </world>
                </instance>
                <instance type="wall">
                    <properties>
                        <initial-visibility>Invisible</initial-visibility>
                        <initial-frame>0</initial-frame>
                        <effect>(none)</effect>
                    </properties>
                    <behavior-instances>
                        <behavior-instance type="Solid" />
                    </behavior-instances>
                    <world>
                        <x>150.5</x>
                        <y>437.5</y>
                        <z>0</z>
                        <width>133</width>
                        <height>47</height>
                        <depth>0</depth>
                        <hotspotX>0.5</hotspotX>
                        <hotspotY>0.5</hotspotY>
                        <angle>0</angle>
                        <opacity>1</opacity>
                    </world>
                </instance>
                <instance type="wall">
                    <properties>
                        <initial-visibility>Invisible</initial-visibility>
                        <initial-frame>0</initial-frame>
                        <effect>(none)</effect>
                    </properties>
                    <behavior-instances>
                        <behavior-instance type="Solid" />
                    </behavior-instances>
                    <world>
                        <x>63</x>
                        <y>428.5</y>
                        <z>0</z>
                        <width>42</width>
                        <height>849</height>
                        <depth>0</depth>
                        <hotspotX>0.5</hotspotX>
                        <hotspotY>0.5</hotspotY>
                        <angle>0</angle>
                        <opacity>1</opacity>
                    </world>
                </instance>
                <instance type="wall">
                    <properties>
                        <initial-visibility>Invisible</initial-visibility>
                        <initial-frame>0</initial-frame>
                        <effect>(none)</effect>
                    </properties>
                    <behavior-instances>
                        <behavior-instance type="Solid" />
                    </behavior-instances>
                    <world>
                        <x>717.5</x>
                        <y>869.5</y>
                        <z>0</z>
                        <width>915</width>
                        <height>37</height>
                        <depth>0</depth>
                        <hotspotX>0.5</hotspotX>
                        <hotspotY>0.5</hotspotY>
                        <angle>0</angle>
                        <opacity>1</opacity>
                    </world>
                </instance>
                <instance type="wall">
                    <properties>
                        <initial-visibility>Invisible</initial-visibility>
                        <initial-frame>0</initial-frame>
                        <effect>(none)</effect>
                    </properties>
                    <behavior-instances>
                        <behavior-instance type="Solid" />
                    </behavior-instances>
                    <world>
                        <x>802.5</x>
                        <y>23.5</y>
                        <z>0</z>
                        <width>743</width>
                        <height>33</height>
                        <depth>0</depth>
                        <hotspotX>0.5</hotspotX>
                        <hotspotY>0.5</hotspotY>
                        <angle>0</angle>
                        <opacity>1</opacity>
                    </world>
                </instance>
                <instance type="wall">
                    <properties>
                        <initial-visibility>Invisible</initial-visibility>
                        <initial-frame>0</initial-frame>
                        <effect>(none)</effect>
                    </properties>
                    <behavior-instances>
                        <behavior-instance type="Solid" />
                    </behavior-instances>
                    <world>
                        <x>257.5</x>
                        <y>25</y>
                        <z>0</z>
                        <width>345</width>
                        <height>44</height>
                        <depth>0</depth>
                        <hotspotX>0.5</hotspotX>
                        <hotspotY>0.5</hotspotY>
                        <angle>0</angle>
                        <opacity>1</opacity>
                    </world>
                </instance>
                <instance type="wall">
                    <properties>
                        <initial-visibility>Invisible</initial-visibility>
                        <initial-frame>0</initial-frame>
                        <effect>(none)</effect>
                    </properties>
                    <behavior-instances>
                        <behavior-instance type="Solid" />
                    </behavior-instances>
                    <world>
                        <x>705.5</x>
                        <y>330.5</y>
                        <z>0</z>
                        <width>45</width>
                        <height>219</height>
                        <depth>0</depth>
                        <hotspotX>0.5</hotspotX>
                        <hotspotY>0.5</hotspotY>
                        <angle>0</angle>
                        <opacity>1</opacity>
                    </world>
                </instance>
                <instance type="door">
                    <properties>
                        <initial-visibility>Invisible</initial-visibility>
                        <initial-frame>0</initial-frame>
                        <effect>(none)</effect>
                    </properties>
                    <instance-variables>
                        <nr>1</nr>
                    </instance-variables>
                    <world>
                        <x>1017.5</x>
                        <y>278</y>
                        <z>0</z>
                        <width>12</width>
                        <height>37</height>
                        <depth>0</depth>
                        <hotspotX>0.5</hotspotX>
                        <hotspotY>0.5</hotspotY>
                        <angle>0</angle>
                        <opacity>1</opacity>
                    </world>
                </instance>
                <instance type="door">
                    <properties>
                        <initial-visibility>Invisible</initial-visibility>
                        <initial-frame>0</initial-frame>
                        <effect>(none)</effect>
                    </properties>
                    <instance-variables>
                        <nr>2</nr>
                    </instance-variables>
                    <world>
                        <x>973</x>
                        <y>443.5</y>
                        <z>0</z>
                        <width>62</width>
                        <height>13</height>
                        <depth>0</depth>
                        <hotspotX>0.5</hotspotX>
                        <hotspotY>0.5</hotspotY>
                        <angle>0</angle>
                        <opacity>1</opacity>
                    </world>
                </instance>
                <instance type="door">
                    <properties>
                        <initial-visibility>Invisible</initial-visibility>
                        <initial-frame>0</initial-frame>
                        <effect>(none)</effect>
                    </properties>
                    <instance-variables>
                        <nr>3</nr>
                    </instance-variables>
                    <world>
                        <x>884</x>
                        <y>604.5</y>
                        <z>0</z>
                        <width>12</width>
                        <height>41</height>
                        <depth>0</depth>
                        <hotspotX>0.5</hotspotX>
                        <hotspotY>0.5</hotspotY>
                        <angle>0</angle>
                        <opacity>1</opacity>
                    </world>
                </instance>
                <instance type="Text">
                    <properties>
                        <text></text>
                        <initial-visibility>Visible</initial-visibility>
                        <font>Arial,-21,400,0</font>
                        <color>102,255,0</color>
                        <horizontal-alignment>Left</horizontal-alignment>
                        <hotspot>Top-left</hotspot>
                    </properties>
                    <world>
                        <x>771</x>
                        <y>8</y>
                        <z>0</z>
                        <width>200</width>
                        <height>30</height>
                        <depth>0</depth>
                        <hotspotX>0</hotspotX>
                        <hotspotY>0</hotspotY>
                        <angle>0</angle>
                        <opacity>1</opacity>
                    </world>
                </instance>
            </instances>
        </layer>
        <layer name="Inventory">
            <initially-visible>1</initially-visible>
            <background-color>255,255,255</background-color>
            <transparent>1</transparent>
            <parallax>
                <x>0</x>
                <y>0</y>
            </parallax>
            <zoom-rate>1</zoom-rate>
            <opacity>1</opacity>
            <force-own-texture>0</force-own-texture>
            <instances>
                <instance type="Sprite">
                    <properties>
                        <initial-visibility>Visible</initial-visibility>
                        <initial-frame>0</initial-frame>
                        <effect>(none)</effect>
                    </properties>
                    <world>
                        <x>40</x>
                        <y>80</y>
                        <z>0</z>
                        <width>80</width>
                        <height>157</height>
                        <depth>0</depth>
                        <hotspotX>0.5</hotspotX>
                        <hotspotY>0.5</hotspotY>
                        <angle>0</angle>
                        <opacity>1</opacity>
                    </world>
                </instance>
            </instances>
        </layer>
    </layers>
    <nonworld-instances />
</c2layout>
